orchagent/__init__.py
orchagent/auth.py
orchagent/chat.py
orchagent/client.py
orchagent/config.py
orchagent/errors.py
orchagent/models.py
orchagent-0.1.3.dist-info/METADATA
orchagent-0.1.3.dist-info/WHEEL
orchagent-0.1.3.dist-info/top_level.txt
orchagent-0.1.3.dist-info/RECORD
