Metadata-Version: 2.4
Name: orchagent
Version: 0.1.3
Summary: Python SDK for the Orchagent API
Author-email: Orchagent <dev@example.com>
Project-URL: Homepage, https://github.com/eladrave/orchagent-python
Requires-Python: >=3.10
Requires-Dist: httpx>=0.28
Requires-Dist: pydantic>=2.7
Requires-Dist: anyio>=4.0
